{"version":1,"resource":"file:///home/sparsha/Desktop/portfolio/index.html","entries":[{"id":"DqQV.html","timestamp":1762953487360},{"id":"lbLv.html","source":"undoRedo.source","timestamp":1763117291516},{"id":"FYBc.html","timestamp":1763117455712},{"id":"vUF8.html","timestamp":1763117497781},{"id":"Drka.html","timestamp":1763117580675},{"id":"QTpP.html","timestamp":1763117643647},{"id":"i04a.html","timestamp":1763117775021},{"id":"aZhj.html","timestamp":1763117832124},{"id":"FkDL.html","timestamp":1763117884049},{"id":"h2rd.html","timestamp":1763117980933},{"id":"ZnZu.html","timestamp":1763117994012},{"id":"vcqu.html","timestamp":1763118010135},{"id":"84IB.html","timestamp":1763118152743},{"id":"In1t.html","timestamp":1763118245982},{"id":"WA8u.html","timestamp":1763118642912},{"id":"xFQf.html","timestamp":1763119079439},{"id":"PRgD.html","timestamp":1763119305846},{"id":"MXAN.html","timestamp":1763119544490},{"id":"5lXZ.html","timestamp":1763119618234},{"id":"t2kz.html","timestamp":1763119635472},{"id":"xKzz.html","timestamp":1763119774154},{"id":"68xU.html","timestamp":1763119917351},{"id":"hzlk.html","timestamp":1763120084700},{"id":"YSKF.html","timestamp":1763120257249},{"id":"k4WQ.html","timestamp":1763120280038},{"id":"nCXB.html","timestamp":1763120316490},{"id":"x8iL.html","timestamp":1763120461302},{"id":"GO5S.html","timestamp":1763120709845},{"id":"xP5a.html","timestamp":1763121323000},{"id":"Qaaj.html","timestamp":1763121377180},{"id":"L2sk.html","timestamp":1763121415938},{"id":"L2BZ.html","timestamp":1763121509151},{"id":"yr38.html","timestamp":1763121612410},{"id":"97Na.html","timestamp":1763121710313}]}