{"version":1,"resource":"file:///home/sparsha/Desktop/portfolio/style.css","entries":[{"id":"e7PE.css","timestamp":1763118566398},{"id":"YHW1.css","timestamp":1763118576981},{"id":"WuFh.css","timestamp":1763118667607},{"id":"uAWX.css","timestamp":1763118710400},{"id":"O8Q7.css","timestamp":1763118741821},{"id":"wSED.css","timestamp":1763118771704},{"id":"qlGt.css","timestamp":1763118794429},{"id":"BFM5.css","timestamp":1763118821034},{"id":"Kodi.css","timestamp":1763118874277},{"id":"tzan.css","timestamp":1763118918643},{"id":"zxMy.css","timestamp":1763118936675},{"id":"TvnA.css","timestamp":1763118953722},{"id":"AVRv.css","timestamp":1763119004249},{"id":"dBl4.css","timestamp":1763119136445},{"id":"bPx1.css","timestamp":1763119183886},{"id":"zgwJ.css","timestamp":1763119199663},{"id":"fcEp.css","timestamp":1763119315493},{"id":"tw5M.css","timestamp":1763119369406},{"id":"JtSC.css","timestamp":1763119384723},{"id":"F7QT.css","timestamp":1763119424919},{"id":"EBcw.css","timestamp":1763119565308},{"id":"OnoR.css","timestamp":1763119810221},{"id":"ONBJ.css","timestamp":1763119948706},{"id":"Hgzd.css","timestamp":1763119970299},{"id":"2yLZ.css","timestamp":1763120095562},{"id":"88cS.css","timestamp":1763120266306},{"id":"9PiT.css","timestamp":1763120325421},{"id":"3vAU.css","timestamp":1763120424429},{"id":"uTP8.css","timestamp":1763120509613},{"id":"6h3c.css","timestamp":1763120520391},{"id":"XuYu.css","timestamp":1763120638150},{"id":"uq33.css","timestamp":1763120709845},{"id":"zXQl.css","timestamp":1763120731461},{"id":"UYWx.css","timestamp":1763120756431},{"id":"OBot.css","timestamp":1763120768477},{"id":"QbDX.css","timestamp":1763120793377},{"id":"H873.css","timestamp":1763120830661},{"id":"IBhj.css","timestamp":1763120861191},{"id":"TG1G.css","timestamp":1763120933607},{"id":"rvaS.css","timestamp":1763121331197},{"id":"zv2K.css","timestamp":1763121389001},{"id":"S6TY.css","timestamp":1763121527826},{"id":"rgKm.css","timestamp":1763121612410},{"id":"hvbr.css","timestamp":1763121746741},{"id":"ucdW.css","timestamp":1763121788713},{"id":"WFoI.css","timestamp":1763121831227},{"id":"kd8y.css","timestamp":1763121972824},{"id":"l6m2.css","timestamp":1763121984367},{"id":"mckl.css","source":"undoRedo.source","timestamp":1763121989783},{"id":"JBZi.css","timestamp":1763122036109}]}